[
  {
    "timestamp": "2026-07-12T19:23:59.944Z",
    "overallStatus": "READY",
    "totalFindings": 0,
    "findingsBySeverity": {
      "P0": 0,
      "P1": 0,
      "P2": 0,
      "P3": 0
    },
    "sentinelScores": {
      "Architecture Sentinel": 100,
      "Build Sentinel": 100,
      "UI Sentinel": 100
    }
  },
  {
    "timestamp": "2026-07-12T19:26:36.811Z",
    "overallStatus": "READY WITH OBSERVATIONS",
    "totalFindings": 0,
    "findingsBySeverity": {
      "P0": 0,
      "P1": 0,
      "P2": 0,
      "P3": 0
    },
    "sentinelScores": {
      "Architecture Sentinel": 0,
      "Build Sentinel": 100,
      "UI Sentinel": 100
    }
  },
  {
    "timestamp": "2026-07-12T19:27:18.984Z",
    "overallStatus": "BLOCKED",
    "totalFindings": 0,
    "findingsBySeverity": {
      "P0": 0,
      "P1": 0,
      "P2": 0,
      "P3": 0
    },
    "sentinelScores": {
      "Architecture Sentinel": 0,
      "Build Sentinel": 100,
      "UI Sentinel": 100
    }
  },
  {
    "timestamp": "2026-07-12T19:36:28.727Z",
    "overallStatus": "READY",
    "totalFindings": 0,
    "findingsBySeverity": {
      "P0": 0,
      "P1": 0,
      "P2": 0,
      "P3": 0
    },
    "sentinelScores": {
      "Architecture Sentinel": 100,
      "Build Sentinel": 100,
      "UI Sentinel": 100
    }
  }
]